fast_pytorch_kmeans/__init__.py
fast_pytorch_kmeans/init_methods.py
fast_pytorch_kmeans/kmeans.py
fast_pytorch_kmeans/multi_kmeans.py
fast_pytorch_kmeans/util.py
fast_pytorch_kmeans-0.2.2.dist-info/LICENSE.txt
fast_pytorch_kmeans-0.2.2.dist-info/METADATA
fast_pytorch_kmeans-0.2.2.dist-info/WHEEL
fast_pytorch_kmeans-0.2.2.dist-info/top_level.txt
fast_pytorch_kmeans-0.2.2.dist-info/RECORD
